Metadata-Version: 2.4
Name: image_processing-DIOFORK
Version: 0.0.1
Summary: Processador de imagens
Home-page: https://github.com/britowb/image-processing-package
Author: BritoWB
Author-email: britowb24@gmail.com
Requires-Python:  >=3.8
Requires-Dist: matplotlib
Requires-Dist: numpy
Requires-Dist: scikit-image>=0.16.1
Dynamic: author
Dynamic: author-email
Dynamic: description
Dynamic: description-content-type
Dynamic: home-page
Dynamic: requires-dist
Dynamic: requires-python
Dynamic: summary
